odoo/addons/repair_order_group/README.rst
odoo/addons/repair_order_group/__init__.py
odoo/addons/repair_order_group/__manifest__.py
odoo/addons/repair_order_group/data/repair_order_group_data.xml
odoo/addons/repair_order_group/demo/repair_order_group_demo.xml
odoo/addons/repair_order_group/i18n/it.po
odoo/addons/repair_order_group/i18n/repair_order_group.pot
odoo/addons/repair_order_group/models/__init__.py
odoo/addons/repair_order_group/models/repair_order.py
odoo/addons/repair_order_group/models/repair_order_group.py
odoo/addons/repair_order_group/readme/CONTEXT.md
odoo/addons/repair_order_group/readme/CONTRIBUTORS.md
odoo/addons/repair_order_group/readme/DESCRIPTION.md
odoo/addons/repair_order_group/readme/USAGE.md
odoo/addons/repair_order_group/readme/newsfragments/.gitkeep
odoo/addons/repair_order_group/security/ir.model.access.csv
odoo/addons/repair_order_group/static/description/icon.png
odoo/addons/repair_order_group/static/description/icon.svg
odoo/addons/repair_order_group/static/description/index.html
odoo/addons/repair_order_group/tests/__init__.py
odoo/addons/repair_order_group/tests/test_repair_order_group.py
odoo/addons/repair_order_group/views/repair_order_group_views.xml
odoo/addons/repair_order_group/views/repair_order_views.xml
odoo_addon_repair_order_group-18.0.1.0.0.3.dist-info/METADATA
odoo_addon_repair_order_group-18.0.1.0.0.3.dist-info/WHEEL
odoo_addon_repair_order_group-18.0.1.0.0.3.dist-info/top_level.txt
odoo_addon_repair_order_group-18.0.1.0.0.3.dist-info/RECORD
