Metadata-Version: 2.1
Name: odoo-addon-repair_order_group
Version: 18.0.1.0.0.3
Requires-Python: >=3.10
Requires-Dist: odoo==18.0.*
Summary: Group several repair orders and keep them in sync
Home-page: https://github.com/OCA/repair
License: AGPL-3
Author: =?utf-8?q?Cetmix_O=C3=9C=2C_Odoo_Community_Association_=28OCA=29?=
Author-email: support@odoo-community.org
Classifier: Programming Language :: Python
Classifier: Framework :: Odoo
Classifier: Framework :: Odoo :: 18.0
Classifier: License :: OSI Approved :: GNU Affero General Public License v3
